{
    "current_program_scene": "Bookcase",
    "current_scene": "Bookcase",
    "current_transition": "Fade",
    "groups": [],
    "modules": {
        "advanced-scene-switcher": {
            "active": true,
            "audioFallbackDuration": 0.0,
            "audioFallbackEnable": false,
            "audioFallbackScene": "",
            "audioFallbackTransition": "",
            "audioSwitches": [],
            "audioTabPos": 12,
            "autoStartEnable": false,
            "autoStartSceneName": "",
            "autoStartType": 0,
            "autoStopEnable": false,
            "autoStopSceneName": "",
            "cooldown": 0.0,
            "defaultTransitions": [],
            "disableHints": false,
            "exeTabPos": 4,
            "executableSwitches": [],
            "fileSwitches": [],
            "fileTabPos": 7,
            "generalTabPos": 0,
            "idleEnable": false,
            "idleSceneName": "",
            "idleTabPos": 10,
            "idleTime": 60,
            "idleTransitionName": "",
            "ignoreIdleWindows": [],
            "ignoreWindows": [],
            "interval": 300,
            "mediaSwitches": [],
            "mediaTabPos": 6,
            "noMatchDelay": 9.4328585525107508e-144,
            "non_matching_scene": "",
            "oldPauseValuesImported": 1,
            "pauseEntries": [],
            "pauseTabPos": 2,
            "priority0": 0,
            "priority1": 1,
            "priority2": 2,
            "priority3": 3,
            "priority4": 4,
            "priority5": 5,
            "priority6": 6,
            "priority7": 7,
            "priority8": 8,
            "randomSwitches": [],
            "randomTabPos": 8,
            "readEnabled": false,
            "readPath": "",
            "regionTabPos": 5,
            "sceneRoundTrip": [],
            "sceneTransitions": [],
            "screenRegion": [],
            "sequenceTabPos": 11,
            "startHotkey": [],
            "startup_behavior": 0,
            "stopHotkey": [],
            "switch_if_not_matching": 0,
            "switches": [],
            "tansitionOverrideOverride": false,
            "threadPriority": 3,
            "timeSwitches": [],
            "timeTabPos": 9,
            "titleTabPos": 3,
            "toggleHotkey": [],
            "transitionTabPos": 1,
            "verbose": false,
            "writeEnabled": false,
            "writePath": ""
        },
        "auto-scene-switcher": {
            "active": false,
            "interval": 300,
            "non_matching_scene": "",
            "switch_if_not_matching": false,
            "switches": []
        },
        "decklink_captions": {
            "source": ""
        },
        "output-timer": {
            "autoStartRecordTimer": false,
            "autoStartStreamTimer": false,
            "pauseRecordTimer": true,
            "recordTimerHours": 0,
            "recordTimerMinutes": 0,
            "recordTimerSeconds": 30,
            "streamTimerHours": 0,
            "streamTimerMinutes": 0,
            "streamTimerSeconds": 30
        },
        "scripts-tool": [],
        "transition-table": {
            "transitions": []
        }
    },
    "name": "Cordince Scenes",
    "preview_locked": false,
    "quick_transitions": [
        {
            "duration": 300,
            "fade_to_black": false,
            "hotkeys": [],
            "id": 7,
            "name": "Cut"
        },
        {
            "duration": 300,
            "fade_to_black": false,
            "hotkeys": [],
            "id": 8,
            "name": "Fade"
        },
        {
            "duration": 300,
            "fade_to_black": true,
            "hotkeys": [],
            "id": 9,
            "name": "Fade"
        }
    ],
    "saved_projectors": [],
    "scaling_enabled": false,
    "scaling_level": 0,
    "scaling_off_x": 0.0,
    "scaling_off_y": 0.0,
    "scene_order": [
        {
            "name": "External Camera"
        },
        {
            "name": "Cordince Center TItle"
        },
        {
            "name": "Lobby Bokeh"
        },
        {
            "name": "Lobby Fire"
        },
        {
            "name": "Cordince Top Left"
        },
        {
            "name": "Cordince Top Left and Title"
        },
        {
            "name": "Pure Subject Black"
        },
        {
            "name": "Pure Subject Gray Gradient"
        },
        {
            "name": "Bookcase"
        },
        {
            "name": "PIP Lower Right"
        }
    ],
    "sources": [
        {
            "balance": 0.5,
            "deinterlace_field_order": 0,
            "deinterlace_mode": 0,
            "enabled": true,
            "filters": [
                {
                    "balance": 0.5,
                    "deinterlace_field_order": 0,
                    "deinterlace_mode": 0,
                    "enabled": true,
                    "flags": 0,
                    "hotkeys": {},
                    "id": "streamfx-filter-blur",
                    "mixers": 0,
                    "monitoring_type": 0,
                    "muted": false,
                    "name": "Blur",
                    "prev_ver": 436273154,
                    "private_settings": {},
                    "push-to-mute": false,
                    "push-to-mute-delay": 0,
                    "push-to-talk": false,
                    "push-to-talk-delay": 0,
                    "settings": {
                        "Commit": "c6fb402d",
                        "Version": 38654836736
                    },
                    "sync": 0,
                    "versioned_id": "streamfx-filter-blur",
                    "volume": 1.0
                }
            ],
            "flags": 0,
            "hotkeys": {},
            "id": "image_source",
            "mixers": 0,
            "monitoring_type": 0,
            "muted": false,
            "name": "office with plant",
            "prev_ver": 436273154,
            "private_settings": {},
            "push-to-mute": false,
            "push-to-mute-delay": 0,
            "push-to-talk": false,
            "push-to-talk-delay": 0,
            "settings": {
                "file": "/home/nharrington/projects/OBS_Cordince/imagery/bookcases/white-plant.jpg"
            },
            "sync": 0,
            "versioned_id": "image_source",
            "volume": 1.0
        },
        {
            "balance": 0.5,
            "deinterlace_field_order": 0,
            "deinterlace_mode": 0,
            "enabled": true,
            "filters": [
                {
                    "balance": 0.5,
                    "deinterlace_field_order": 0,
                    "deinterlace_mode": 0,
                    "enabled": false,
                    "flags": 0,
                    "hotkeys": {},
                    "id": "color_filter",
                    "mixers": 0,
                    "monitoring_type": 0,
                    "muted": false,
                    "name": "Color Correction",
                    "prev_ver": 436273154,
                    "private_settings": {},
                    "push-to-mute": false,
                    "push-to-mute-delay": 0,
                    "push-to-talk": false,
                    "push-to-talk-delay": 0,
                    "settings": {
                        "hue_shift": 180.0,
                        "saturation": 2.0099999999999998
                    },
                    "sync": 0,
                    "versioned_id": "color_filter",
                    "volume": 1.0
                },
                {
                    "balance": 0.5,
                    "deinterlace_field_order": 0,
                    "deinterlace_mode": 0,
                    "enabled": true,
                    "flags": 0,
                    "hotkeys": {},
                    "id": "streamfx-filter-blur",
                    "mixers": 0,
                    "monitoring_type": 0,
                    "muted": false,
                    "name": "Blur",
                    "prev_ver": 436273154,
                    "private_settings": {},
                    "push-to-mute": false,
                    "push-to-mute-delay": 0,
                    "push-to-talk": false,
                    "push-to-talk-delay": 0,
                    "settings": {
                        "Commit": "c6fb402d",
                        "Version": 38654836736
                    },
                    "sync": 0,
                    "versioned_id": "streamfx-filter-blur",
                    "volume": 1.0
                },
                {
                    "balance": 0.5,
                    "deinterlace_field_order": 0,
                    "deinterlace_mode": 0,
                    "enabled": true,
                    "flags": 0,
                    "hotkeys": {},
                    "id": "rgb_levels_filter",
                    "mixers": 0,
                    "monitoring_type": 0,
                    "muted": false,
                    "name": "RGB levels",
                    "prev_ver": 436273154,
                    "private_settings": {},
                    "push-to-mute": false,
                    "push-to-mute-delay": 0,
                    "push-to-talk": false,
                    "push-to-talk-delay": 0,
                    "settings": {},
                    "sync": 0,
                    "versioned_id": "rgb_levels_filter",
                    "volume": 1.0
                }
            ],
            "flags": 0,
            "hotkeys": {},
            "id": "image_source",
            "mixers": 0,
            "monitoring_type": 0,
            "muted": false,
            "name": "standing office",
            "prev_ver": 436273154,
            "private_settings": {},
            "push-to-mute": false,
            "push-to-mute-delay": 0,
            "push-to-talk": false,
            "push-to-talk-delay": 0,
            "settings": {
                "file": "/home/nharrington/projects/OBS_Cordince/imagery/bookcases/standing-office.jpg"
            },
            "sync": 0,
            "versioned_id": "image_source",
            "volume": 1.0
        },
        {
            "balance": 0.5,
            "deinterlace_field_order": 0,
            "deinterlace_mode": 0,
            "enabled": true,
            "filters": [
                {
                    "balance": 0.5,
                    "deinterlace_field_order": 0,
                    "deinterlace_mode": 0,
                    "enabled": true,
                    "flags": 0,
                    "hotkeys": {},
                    "id": "streamfx-filter-blur",
                    "mixers": 0,
                    "monitoring_type": 0,
                    "muted": false,
                    "name": "Blur",
                    "prev_ver": 436273154,
                    "private_settings": {},
                    "push-to-mute": false,
                    "push-to-mute-delay": 0,
                    "push-to-talk": false,
                    "push-to-talk-delay": 0,
                    "settings": {
                        "Commit": "c6fb402d",
                        "Version": 38654836736
                    },
                    "sync": 0,
                    "versioned_id": "streamfx-filter-blur",
                    "volume": 1.0
                }
            ],
            "flags": 0,
            "hotkeys": {},
            "id": "image_source",
            "mixers": 0,
            "monitoring_type": 0,
            "muted": false,
            "name": "white grid",
            "prev_ver": 436273154,
            "private_settings": {},
            "push-to-mute": false,
            "push-to-mute-delay": 0,
            "push-to-talk": false,
            "push-to-talk-delay": 0,
            "settings": {
                "file": "/home/nharrington/projects/OBS_Cordince/imagery/bookcases/gridbackground1.jpg"
            },
            "sync": 0,
            "versioned_id": "image_source",
            "volume": 1.0
        },
        {
            "balance": 0.5,
            "deinterlace_field_order": 0,
            "deinterlace_mode": 0,
            "enabled": true,
            "filters": [
                {
                    "balance": 0.5,
                    "deinterlace_field_order": 0,
                    "deinterlace_mode": 0,
                    "enabled": true,
                    "flags": 0,
                    "hotkeys": {},
                    "id": "streamfx-filter-blur",
                    "mixers": 0,
                    "monitoring_type": 0,
                    "muted": false,
                    "name": "Blur",
                    "prev_ver": 436273154,
                    "private_settings": {},
                    "push-to-mute": false,
                    "push-to-mute-delay": 0,
                    "push-to-talk": false,
                    "push-to-talk-delay": 0,
                    "settings": {
                        "Commit": "c6fb402d",
                        "Version": 38654836736
                    },
                    "sync": 0,
                    "versioned_id": "streamfx-filter-blur",
                    "volume": 1.0
                }
            ],
            "flags": 0,
            "hotkeys": {},
            "id": "image_source",
            "mixers": 0,
            "monitoring_type": 0,
            "muted": false,
            "name": "white room",
            "prev_ver": 436273154,
            "private_settings": {},
            "push-to-mute": false,
            "push-to-mute-delay": 0,
            "push-to-talk": false,
            "push-to-talk-delay": 0,
            "settings": {
                "file": "/home/nharrington/projects/OBS_Cordince/imagery/bookcases/Erickson_7504.0.jpg"
            },
            "sync": 0,
            "versioned_id": "image_source",
            "volume": 1.0
        },
        {
            "balance": 0.5,
            "deinterlace_field_order": 0,
            "deinterlace_mode": 0,
            "enabled": true,
            "filters": [
                {
                    "balance": 0.5,
                    "deinterlace_field_order": 0,
                    "deinterlace_mode": 0,
                    "enabled": true,
                    "flags": 0,
                    "hotkeys": {},
                    "id": "streamfx-filter-blur",
                    "mixers": 0,
                    "monitoring_type": 0,
                    "muted": false,
                    "name": "Blur",
                    "prev_ver": 436273154,
                    "private_settings": {},
                    "push-to-mute": false,
                    "push-to-mute-delay": 0,
                    "push-to-talk": false,
                    "push-to-talk-delay": 0,
                    "settings": {
                        "Commit": "c6fb402d",
                        "Filter.Blur.Size": 6.0,
                        "Version": 38654836736
                    },
                    "sync": 0,
                    "versioned_id": "streamfx-filter-blur",
                    "volume": 1.0
                }
            ],
            "flags": 0,
            "hotkeys": {},
            "id": "image_source",
            "mixers": 0,
            "monitoring_type": 0,
            "muted": false,
            "name": "dark case",
            "prev_ver": 436273154,
            "private_settings": {},
            "push-to-mute": false,
            "push-to-mute-delay": 0,
            "push-to-talk": false,
            "push-to-talk-delay": 0,
            "settings": {
                "file": "/home/nharrington/projects/OBS_Cordince/imagery/bookcases/dark-case.jpg"
            },
            "sync": 0,
            "versioned_id": "image_source",
            "volume": 1.0
        },
        {
            "balance": 0.5,
            "deinterlace_field_order": 0,
            "deinterlace_mode": 0,
            "enabled": true,
            "filters": [
                {
                    "balance": 0.5,
                    "deinterlace_field_order": 0,
                    "deinterlace_mode": 0,
                    "enabled": true,
                    "flags": 0,
                    "hotkeys": {},
                    "id": "streamfx-filter-blur",
                    "mixers": 0,
                    "monitoring_type": 0,
                    "muted": false,
                    "name": "Blur",
                    "prev_ver": 436273154,
                    "private_settings": {},
                    "push-to-mute": false,
                    "push-to-mute-delay": 0,
                    "push-to-talk": false,
                    "push-to-talk-delay": 0,
                    "settings": {
                        "Commit": "c6fb402d",
                        "Filter.Blur.Size": 7.0,
                        "Version": 38654836736
                    },
                    "sync": 0,
                    "versioned_id": "streamfx-filter-blur",
                    "volume": 1.0
                }
            ],
            "flags": 0,
            "hotkeys": {},
            "id": "image_source",
            "mixers": 0,
            "monitoring_type": 0,
            "muted": false,
            "name": "brown real case",
            "prev_ver": 436273154,
            "private_settings": {},
            "push-to-mute": false,
            "push-to-mute-delay": 0,
            "push-to-talk": false,
            "push-to-talk-delay": 0,
            "settings": {
                "file": "/home/nharrington/projects/OBS_Cordince/imagery/bookcases/brown-case.jpg"
            },
            "sync": 0,
            "versioned_id": "image_source",
            "volume": 1.0
        },
        {
            "balance": 0.5,
            "deinterlace_field_order": 0,
            "deinterlace_mode": 0,
            "enabled": true,
            "flags": 0,
            "hotkeys": {},
            "id": "image_source",
            "mixers": 0,
            "monitoring_type": 0,
            "muted": false,
            "name": "white ladder",
            "prev_ver": 436273154,
            "private_settings": {},
            "push-to-mute": false,
            "push-to-mute-delay": 0,
            "push-to-talk": false,
            "push-to-talk-delay": 0,
            "settings": {
                "file": "/home/nharrington/projects/OBS_Cordince/imagery/bookcases/00-FEATURE-how-to-style-book-shelf-domino-3x4.jpg"
            },
            "sync": 0,
            "versioned_id": "image_source",
            "volume": 1.0
        },
        {
            "balance": 0.5,
            "deinterlace_field_order": 0,
            "deinterlace_mode": 0,
            "enabled": true,
            "flags": 0,
            "hotkeys": {},
            "id": "gradient_source",
            "mixers": 0,
            "monitoring_type": 0,
            "muted": false,
            "name": "Gradient Gray",
            "prev_ver": 436273154,
            "private_settings": {},
            "push-to-mute": false,
            "push-to-mute-delay": 0,
            "push-to-talk": false,
            "push-to-talk-delay": 0,
            "settings": {
                "rotation": 360.0,
                "to_color": 4287137928
            },
            "sync": 0,
            "versioned_id": "gradient_source",
            "volume": 1.0
        },
        {
            "balance": 0.5,
            "deinterlace_field_order": 0,
            "deinterlace_mode": 0,
            "enabled": true,
            "flags": 0,
            "hotkeys": {
                "OBSBasic.SelectScene": [],
                "libobs.hide_scene_item.External Camera": [],
                "libobs.hide_scene_item.brown real case": [],
                "libobs.hide_scene_item.dark case": [],
                "libobs.hide_scene_item.office with plant": [],
                "libobs.hide_scene_item.standing office": [],
                "libobs.hide_scene_item.white grid": [],
                "libobs.hide_scene_item.white ladder": [],
                "libobs.hide_scene_item.white room": [],
                "libobs.show_scene_item.External Camera": [],
                "libobs.show_scene_item.brown real case": [],
                "libobs.show_scene_item.dark case": [],
                "libobs.show_scene_item.office with plant": [],
                "libobs.show_scene_item.standing office": [],
                "libobs.show_scene_item.white grid": [],
                "libobs.show_scene_item.white ladder": [],
                "libobs.show_scene_item.white room": []
            },
            "id": "scene",
            "mixers": 0,
            "monitoring_type": 0,
            "muted": false,
            "name": "Bookcase",
            "prev_ver": 436273154,
            "private_settings": {},
            "push-to-mute": false,
            "push-to-mute-delay": 0,
            "push-to-talk": false,
            "push-to-talk-delay": 0,
            "settings": {
                "custom_size": false,
                "id_counter": 13,
                "items": [
                    {
                        "align": 5,
                        "bounds": {
                            "x": 0.0,
                            "y": 0.0
                        },
                        "bounds_align": 0,
                        "bounds_type": 0,
                        "crop_bottom": 0,
                        "crop_left": 0,
                        "crop_right": 0,
                        "crop_top": 0,
                        "group_item_backup": false,
                        "id": 8,
                        "locked": false,
                        "name": "white room",
                        "pos": {
                            "x": 0.0,
                            "y": 0.0
                        },
                        "private_settings": {},
                        "rot": 0.0,
                        "scale": {
                            "x": 1.6000000238418579,
                            "y": 1.6000000238418579
                        },
                        "scale_filter": "disable",
                        "visible": false
                    },
                    {
                        "align": 5,
                        "bounds": {
                            "x": 0.0,
                            "y": 0.0
                        },
                        "bounds_align": 0,
                        "bounds_type": 0,
                        "crop_bottom": 0,
                        "crop_left": 0,
                        "crop_right": 0,
                        "crop_top": 0,
                        "group_item_backup": false,
                        "id": 10,
                        "locked": false,
                        "name": "standing office",
                        "pos": {
                            "x": 0.0,
                            "y": 0.0
                        },
                        "private_settings": {},
                        "rot": 0.0,
                        "scale": {
                            "x": 1.1866501569747925,
                            "y": 1.1870369911193848
                        },
                        "scale_filter": "disable",
                        "visible": false
                    },
                    {
                        "align": 5,
                        "bounds": {
                            "x": 0.0,
                            "y": 0.0
                        },
                        "bounds_align": 0,
                        "bounds_type": 0,
                        "crop_bottom": 0,
                        "crop_left": 0,
                        "crop_right": 0,
                        "crop_top": 0,
                        "group_item_backup": false,
                        "id": 2,
                        "locked": false,
                        "name": "white ladder",
                        "pos": {
                            "x": 0.0,
                            "y": 0.0
                        },
                        "private_settings": {},
                        "rot": 0.0,
                        "scale": {
                            "x": 1.7424999475479126,
                            "y": 1.7428570985794067
                        },
                        "scale_filter": "disable",
                        "visible": false
                    },
                    {
                        "align": 5,
                        "bounds": {
                            "x": 0.0,
                            "y": 0.0
                        },
                        "bounds_align": 0,
                        "bounds_type": 0,
                        "crop_bottom": 0,
                        "crop_left": 0,
                        "crop_right": 0,
                        "crop_top": 0,
                        "group_item_backup": false,
                        "id": 12,
                        "locked": false,
                        "name": "office with plant",
                        "pos": {
                            "x": 0.0,
                            "y": 0.0
                        },
                        "private_settings": {},
                        "rot": 0.0,
                        "scale": {
                            "x": 1.5153906345367432,
                            "y": 1.5157407522201538
                        },
                        "scale_filter": "disable",
                        "visible": false
                    },
                    {
                        "align": 5,
                        "bounds": {
                            "x": 0.0,
                            "y": 0.0
                        },
                        "bounds_align": 0,
                        "bounds_type": 0,
                        "crop_bottom": 0,
                        "crop_left": 0,
                        "crop_right": 0,
                        "crop_top": 0,
                        "group_item_backup": false,
                        "id": 5,
                        "locked": false,
                        "name": "brown real case",
                        "pos": {
                            "x": 0.0,
                            "y": 0.0
                        },
                        "private_settings": {},
                        "rot": 0.0,
                        "scale": {
                            "x": 1.1866501569747925,
                            "y": 1.1870369911193848
                        },
                        "scale_filter": "disable",
                        "visible": false
                    },
                    {
                        "align": 5,
                        "bounds": {
                            "x": 0.0,
                            "y": 0.0
                        },
                        "bounds_align": 0,
                        "bounds_type": 0,
                        "crop_bottom": 0,
                        "crop_left": 0,
                        "crop_right": 0,
                        "crop_top": 0,
                        "group_item_backup": false,
                        "id": 9,
                        "locked": false,
                        "name": "white grid",
                        "pos": {
                            "x": 0.0,
                            "y": 0.0
                        },
                        "private_settings": {},
                        "rot": 0.0,
                        "scale": {
                            "x": 1.25,
                            "y": 1.25
                        },
                        "scale_filter": "disable",
                        "visible": false
                    },
                    {
                        "align": 5,
                        "bounds": {
                            "x": 0.0,
                            "y": 0.0
                        },
                        "bounds_align": 0,
                        "bounds_type": 0,
                        "crop_bottom": 0,
                        "crop_left": 0,
                        "crop_right": 0,
                        "crop_top": 0,
                        "group_item_backup": false,
                        "id": 7,
                        "locked": false,
                        "name": "dark case",
                        "pos": {
                            "x": 0.0,
                            "y": 0.0
                        },
                        "private_settings": {},
                        "rot": 0.0,
                        "scale": {
                            "x": 1.1851851940155029,
                            "y": 1.1851851940155029
                        },
                        "scale_filter": "disable",
                        "visible": true
                    },
                    {
                        "align": 5,
                        "bounds": {
                            "x": 0.0,
                            "y": 0.0
                        },
                        "bounds_align": 0,
                        "bounds_type": 0,
                        "crop_bottom": 0,
                        "crop_left": 0,
                        "crop_right": 0,
                        "crop_top": 0,
                        "group_item_backup": false,
                        "id": 13,
                        "locked": false,
                        "name": "External Camera",
                        "pos": {
                            "x": 0.0,
                            "y": 0.0
                        },
                        "private_settings": {},
                        "rot": 0.0,
                        "scale": {
                            "x": 1.0,
                            "y": 1.0
                        },
                        "scale_filter": "disable",
                        "visible": true
                    }
                ]
            },
            "sync": 0,
            "versioned_id": "scene",
            "volume": 1.0
        },
        {
            "balance": 0.5,
            "deinterlace_field_order": 0,
            "deinterlace_mode": 0,
            "enabled": true,
            "flags": 0,
            "hotkeys": {
                "OBSBasic.SelectScene": [],
                "libobs.hide_scene_item.External Camera": [],
                "libobs.hide_scene_item.Gradient Gray": [],
                "libobs.show_scene_item.External Camera": [],
                "libobs.show_scene_item.Gradient Gray": []
            },
            "id": "scene",
            "mixers": 0,
            "monitoring_type": 0,
            "muted": false,
            "name": "Pure Subject Gray Gradient",
            "prev_ver": 436273154,
            "private_settings": {},
            "push-to-mute": false,
            "push-to-mute-delay": 0,
            "push-to-talk": false,
            "push-to-talk-delay": 0,
            "settings": {
                "custom_size": false,
                "id_counter": 2,
                "items": [
                    {
                        "align": 5,
                        "bounds": {
                            "x": 0.0,
                            "y": 0.0
                        },
                        "bounds_align": 0,
                        "bounds_type": 0,
                        "crop_bottom": 0,
                        "crop_left": 0,
                        "crop_right": 0,
                        "crop_top": 0,
                        "group_item_backup": false,
                        "id": 1,
                        "locked": false,
                        "name": "Gradient Gray",
                        "pos": {
                            "x": 0.0,
                            "y": 0.0
                        },
                        "private_settings": {},
                        "rot": 0.0,
                        "scale": {
                            "x": 1.0,
                            "y": 1.0
                        },
                        "scale_filter": "disable",
                        "visible": true
                    },
                    {
                        "align": 5,
                        "bounds": {
                            "x": 0.0,
                            "y": 0.0
                        },
                        "bounds_align": 0,
                        "bounds_type": 0,
                        "crop_bottom": 0,
                        "crop_left": 0,
                        "crop_right": 0,
                        "crop_top": 0,
                        "group_item_backup": false,
                        "id": 2,
                        "locked": false,
                        "name": "External Camera",
                        "pos": {
                            "x": 0.0,
                            "y": 0.0
                        },
                        "private_settings": {},
                        "rot": 0.0,
                        "scale": {
                            "x": 1.0,
                            "y": 1.0
                        },
                        "scale_filter": "disable",
                        "visible": true
                    }
                ]
            },
            "sync": 0,
            "versioned_id": "scene",
            "volume": 1.0
        },
        {
            "balance": 0.5,
            "deinterlace_field_order": 0,
            "deinterlace_mode": 0,
            "enabled": true,
            "flags": 0,
            "hotkeys": {},
            "id": "text_ft2_source",
            "mixers": 0,
            "monitoring_type": 0,
            "muted": false,
            "name": "Nathan Harrington",
            "prev_ver": 436273154,
            "private_settings": {},
            "push-to-mute": false,
            "push-to-mute-delay": 0,
            "push-to-talk": false,
            "push-to-talk-delay": 0,
            "settings": {
                "drop_shadow": true,
                "font": {
                    "face": "Proxima Nova",
                    "flags": 1,
                    "size": 48,
                    "style": "Bold"
                },
                "text": "Nathan Harrington"
            },
            "sync": 0,
            "versioned_id": "text_ft2_source_v2",
            "volume": 1.0
        },
        {
            "balance": 0.5,
            "deinterlace_field_order": 0,
            "deinterlace_mode": 0,
            "enabled": true,
            "flags": 0,
            "hotkeys": {
                "OBSBasic.SelectScene": [],
                "libobs.hide_scene_item.Cordince": [],
                "libobs.hide_scene_item.External Camera": [],
                "libobs.hide_scene_item.Logo": [],
                "libobs.hide_scene_item.Nathan Harrington": [],
                "libobs.show_scene_item.Cordince": [],
                "libobs.show_scene_item.External Camera": [],
                "libobs.show_scene_item.Logo": [],
                "libobs.show_scene_item.Nathan Harrington": []
            },
            "id": "scene",
            "mixers": 0,
            "monitoring_type": 0,
            "muted": false,
            "name": "Cordince Top Left and Title",
            "prev_ver": 436273154,
            "private_settings": {},
            "push-to-mute": false,
            "push-to-mute-delay": 0,
            "push-to-talk": false,
            "push-to-talk-delay": 0,
            "settings": {
                "custom_size": false,
                "id_counter": 5,
                "items": [
                    {
                        "align": 5,
                        "bounds": {
                            "x": 0.0,
                            "y": 0.0
                        },
                        "bounds_align": 0,
                        "bounds_type": 0,
                        "crop_bottom": 0,
                        "crop_left": 0,
                        "crop_right": 0,
                        "crop_top": 0,
                        "group_item_backup": false,
                        "id": 1,
                        "locked": false,
                        "name": "External Camera",
                        "pos": {
                            "x": -2.0,
                            "y": 0.0
                        },
                        "private_settings": {},
                        "rot": 0.0,
                        "scale": {
                            "x": 1.0,
                            "y": 1.0
                        },
                        "scale_filter": "disable",
                        "visible": true
                    },
                    {
                        "align": 5,
                        "bounds": {
                            "x": 0.0,
                            "y": 0.0
                        },
                        "bounds_align": 0,
                        "bounds_type": 0,
                        "crop_bottom": 0,
                        "crop_left": 0,
                        "crop_right": 0,
                        "crop_top": 0,
                        "group_item_backup": false,
                        "id": 2,
                        "locked": false,
                        "name": "Logo",
                        "pos": {
                            "x": 27.0,
                            "y": 21.0
                        },
                        "private_settings": {},
                        "rot": 0.0,
                        "scale": {
                            "x": 0.092000000178813934,
                            "y": 0.092000000178813934
                        },
                        "scale_filter": "disable",
                        "visible": true
                    },
                    {
                        "align": 5,
                        "bounds": {
                            "x": 0.0,
                            "y": 0.0
                        },
                        "bounds_align": 0,
                        "bounds_type": 0,
                        "crop_bottom": 0,
                        "crop_left": 0,
                        "crop_right": 0,
                        "crop_top": 0,
                        "group_item_backup": false,
                        "id": 3,
                        "locked": false,
                        "name": "Cordince",
                        "pos": {
                            "x": 122.0,
                            "y": 26.0
                        },
                        "private_settings": {},
                        "rot": 0.0,
                        "scale": {
                            "x": 1.0,
                            "y": 1.0
                        },
                        "scale_filter": "disable",
                        "visible": true
                    },
                    {
                        "align": 5,
                        "bounds": {
                            "x": 0.0,
                            "y": 0.0
                        },
                        "bounds_align": 0,
                        "bounds_type": 0,
                        "crop_bottom": 0,
                        "crop_left": 0,
                        "crop_right": 0,
                        "crop_top": 0,
                        "group_item_backup": false,
                        "id": 5,
                        "locked": false,
                        "name": "Nathan Harrington",
                        "pos": {
                            "x": 1470.0,
                            "y": 991.0
                        },
                        "private_settings": {},
                        "rot": 0.0,
                        "scale": {
                            "x": 1.0,
                            "y": 1.0
                        },
                        "scale_filter": "disable",
                        "visible": true
                    }
                ]
            },
            "sync": 0,
            "versioned_id": "scene",
            "volume": 1.0
        },
        {
            "balance": 0.5,
            "deinterlace_field_order": 0,
            "deinterlace_mode": 0,
            "enabled": true,
            "flags": 0,
            "hotkeys": {
                "OBSBasic.SelectScene": [],
                "libobs.hide_scene_item.External Camera": [],
                "libobs.show_scene_item.External Camera": []
            },
            "id": "scene",
            "mixers": 0,
            "monitoring_type": 0,
            "muted": false,
            "name": "PIP Lower Right",
            "prev_ver": 436273154,
            "private_settings": {},
            "push-to-mute": false,
            "push-to-mute-delay": 0,
            "push-to-talk": false,
            "push-to-talk-delay": 0,
            "settings": {
                "custom_size": false,
                "id_counter": 1,
                "items": [
                    {
                        "align": 5,
                        "bounds": {
                            "x": 0.0,
                            "y": 0.0
                        },
                        "bounds_align": 0,
                        "bounds_type": 0,
                        "crop_bottom": 0,
                        "crop_left": 0,
                        "crop_right": 0,
                        "crop_top": 0,
                        "group_item_backup": false,
                        "id": 1,
                        "locked": false,
                        "name": "External Camera",
                        "pos": {
                            "x": 1500.0,
                            "y": 844.0
                        },
                        "private_settings": {},
                        "rot": 0.0,
                        "scale": {
                            "x": 0.21875,
                            "y": 0.21851852536201477
                        },
                        "scale_filter": "disable",
                        "visible": true
                    }
                ]
            },
            "sync": 0,
            "versioned_id": "scene",
            "volume": 1.0
        },
        {
            "balance": 0.5,
            "deinterlace_field_order": 0,
            "deinterlace_mode": 0,
            "enabled": true,
            "flags": 0,
            "hotkeys": {
                "OBSBasic.SelectScene": [],
                "libobs.hide_scene_item.External Camera": [],
                "libobs.show_scene_item.External Camera": []
            },
            "id": "scene",
            "mixers": 0,
            "monitoring_type": 0,
            "muted": false,
            "name": "Pure Subject Black",
            "prev_ver": 436273154,
            "private_settings": {},
            "push-to-mute": false,
            "push-to-mute-delay": 0,
            "push-to-talk": false,
            "push-to-talk-delay": 0,
            "settings": {
                "custom_size": false,
                "id_counter": 4,
                "items": [
                    {
                        "align": 5,
                        "bounds": {
                            "x": 0.0,
                            "y": 0.0
                        },
                        "bounds_align": 0,
                        "bounds_type": 0,
                        "crop_bottom": 0,
                        "crop_left": 0,
                        "crop_right": 0,
                        "crop_top": 0,
                        "group_item_backup": false,
                        "id": 1,
                        "locked": false,
                        "name": "External Camera",
                        "pos": {
                            "x": 0.0,
                            "y": 0.0
                        },
                        "private_settings": {},
                        "rot": 0.0,
                        "scale": {
                            "x": 1.0,
                            "y": 1.0
                        },
                        "scale_filter": "disable",
                        "visible": true
                    }
                ]
            },
            "sync": 0,
            "versioned_id": "scene",
            "volume": 1.0
        },
        {
            "balance": 0.5,
            "deinterlace_field_order": 0,
            "deinterlace_mode": 0,
            "enabled": true,
            "filters": [
                {
                    "balance": 0.5,
                    "deinterlace_field_order": 0,
                    "deinterlace_mode": 0,
                    "enabled": true,
                    "flags": 0,
                    "hotkeys": {},
                    "id": "chroma_key_filter",
                    "mixers": 0,
                    "monitoring_type": 0,
                    "muted": false,
                    "name": "Chroma Key",
                    "prev_ver": 436273154,
                    "private_settings": {},
                    "push-to-mute": false,
                    "push-to-mute-delay": 0,
                    "push-to-talk": false,
                    "push-to-talk-delay": 0,
                    "settings": {
                        "similarity": 438
                    },
                    "sync": 0,
                    "versioned_id": "chroma_key_filter",
                    "volume": 1.0
                }
            ],
            "flags": 0,
            "hotkeys": {},
            "id": "v4l2_input",
            "mixers": 0,
            "monitoring_type": 0,
            "muted": false,
            "name": "Video Capture Device (V4L2)",
            "prev_ver": 436273154,
            "private_settings": {},
            "push-to-mute": false,
            "push-to-mute-delay": 0,
            "push-to-talk": false,
            "push-to-talk-delay": 0,
            "settings": {
                "device_id": "/dev/v4l/by-path/pci-0000:00:14.0-usb-0:1:1.0-video-index0",
                "input": 0,
                "pixelformat": 1448695129
            },
            "sync": 0,
            "versioned_id": "v4l2_input",
            "volume": 1.0
        },
        {
            "balance": 0.5,
            "deinterlace_field_order": 0,
            "deinterlace_mode": 0,
            "enabled": true,
            "flags": 0,
            "hotkeys": {},
            "id": "text_ft2_source",
            "mixers": 0,
            "monitoring_type": 0,
            "muted": false,
            "name": "Joining shortly",
            "prev_ver": 436273154,
            "private_settings": {},
            "push-to-mute": false,
            "push-to-mute-delay": 0,
            "push-to-talk": false,
            "push-to-talk-delay": 0,
            "settings": {
                "drop_shadow": true,
                "font": {
                    "face": "Proxima Nova",
                    "flags": 1,
                    "size": 36,
                    "style": "Bold"
                },
                "outline": true,
                "text": "Joining Shortly..."
            },
            "sync": 0,
            "versioned_id": "text_ft2_source_v2",
            "volume": 1.0
        },
        {
            "balance": 0.5,
            "deinterlace_field_order": 0,
            "deinterlace_mode": 0,
            "enabled": true,
            "flags": 0,
            "hotkeys": {
                "OBSBasic.SelectScene": [],
                "libobs.hide_scene_item.Cordince": [],
                "libobs.hide_scene_item.External Camera": [],
                "libobs.hide_scene_item.Logo": [],
                "libobs.show_scene_item.Cordince": [],
                "libobs.show_scene_item.External Camera": [],
                "libobs.show_scene_item.Logo": []
            },
            "id": "scene",
            "mixers": 0,
            "monitoring_type": 0,
            "muted": false,
            "name": "Cordince Top Left",
            "prev_ver": 436273154,
            "private_settings": {},
            "push-to-mute": false,
            "push-to-mute-delay": 0,
            "push-to-talk": false,
            "push-to-talk-delay": 0,
            "settings": {
                "custom_size": false,
                "id_counter": 7,
                "items": [
                    {
                        "align": 5,
                        "bounds": {
                            "x": 0.0,
                            "y": 0.0
                        },
                        "bounds_align": 0,
                        "bounds_type": 0,
                        "crop_bottom": 0,
                        "crop_left": 0,
                        "crop_right": 0,
                        "crop_top": 0,
                        "group_item_backup": false,
                        "id": 7,
                        "locked": false,
                        "name": "External Camera",
                        "pos": {
                            "x": 0.0,
                            "y": 0.0
                        },
                        "private_settings": {},
                        "rot": 0.0,
                        "scale": {
                            "x": 1.0,
                            "y": 1.0
                        },
                        "scale_filter": "disable",
                        "visible": true
                    },
                    {
                        "align": 5,
                        "bounds": {
                            "x": 0.0,
                            "y": 0.0
                        },
                        "bounds_align": 0,
                        "bounds_type": 0,
                        "crop_bottom": 0,
                        "crop_left": 0,
                        "crop_right": 0,
                        "crop_top": 0,
                        "group_item_backup": false,
                        "id": 5,
                        "locked": false,
                        "name": "Logo",
                        "pos": {
                            "x": 27.0,
                            "y": 21.0
                        },
                        "private_settings": {},
                        "rot": 0.0,
                        "scale": {
                            "x": 0.092000000178813934,
                            "y": 0.092000000178813934
                        },
                        "scale_filter": "disable",
                        "visible": true
                    },
                    {
                        "align": 5,
                        "bounds": {
                            "x": 0.0,
                            "y": 0.0
                        },
                        "bounds_align": 0,
                        "bounds_type": 0,
                        "crop_bottom": 0,
                        "crop_left": 0,
                        "crop_right": 0,
                        "crop_top": 0,
                        "group_item_backup": false,
                        "id": 6,
                        "locked": false,
                        "name": "Cordince",
                        "pos": {
                            "x": 123.0,
                            "y": 26.0
                        },
                        "private_settings": {},
                        "rot": 0.0,
                        "scale": {
                            "x": 1.0,
                            "y": 1.0
                        },
                        "scale_filter": "disable",
                        "visible": true
                    }
                ]
            },
            "sync": 0,
            "versioned_id": "scene",
            "volume": 1.0
        },
        {
            "balance": 0.5,
            "deinterlace_field_order": 0,
            "deinterlace_mode": 0,
            "enabled": true,
            "flags": 0,
            "hotkeys": {
                "OBSBasic.SelectScene": [],
                "libobs.hide_scene_item.Bokeh Desaturated Top Blur": [],
                "libobs.hide_scene_item.Cordince Center TItle": [],
                "libobs.show_scene_item.Bokeh Desaturated Top Blur": [],
                "libobs.show_scene_item.Cordince Center TItle": []
            },
            "id": "scene",
            "mixers": 0,
            "monitoring_type": 0,
            "muted": false,
            "name": "Lobby Bokeh",
            "prev_ver": 436273154,
            "private_settings": {},
            "push-to-mute": false,
            "push-to-mute-delay": 0,
            "push-to-talk": false,
            "push-to-talk-delay": 0,
            "settings": {
                "custom_size": false,
                "id_counter": 13,
                "items": [
                    {
                        "align": 5,
                        "bounds": {
                            "x": 1920.0,
                            "y": 1080.0
                        },
                        "bounds_align": 0,
                        "bounds_type": 2,
                        "crop_bottom": 0,
                        "crop_left": 0,
                        "crop_right": 0,
                        "crop_top": 0,
                        "group_item_backup": false,
                        "id": 6,
                        "locked": false,
                        "name": "Bokeh Desaturated Top Blur",
                        "pos": {
                            "x": 0.0,
                            "y": 0.0
                        },
                        "private_settings": {},
                        "rot": 0.0,
                        "scale": {
                            "x": 1.0,
                            "y": 1.0
                        },
                        "scale_filter": "disable",
                        "visible": true
                    },
                    {
                        "align": 5,
                        "bounds": {
                            "x": 0.0,
                            "y": 0.0
                        },
                        "bounds_align": 0,
                        "bounds_type": 0,
                        "crop_bottom": 0,
                        "crop_left": 0,
                        "crop_right": 0,
                        "crop_top": 0,
                        "group_item_backup": false,
                        "id": 13,
                        "locked": false,
                        "name": "Cordince Center TItle",
                        "pos": {
                            "x": 0.0,
                            "y": 0.0
                        },
                        "private_settings": {},
                        "rot": 0.0,
                        "scale": {
                            "x": 1.0,
                            "y": 1.0
                        },
                        "scale_filter": "disable",
                        "visible": true
                    }
                ]
            },
            "sync": 0,
            "versioned_id": "scene",
            "volume": 1.0
        },
        {
            "balance": 0.5,
            "deinterlace_field_order": 0,
            "deinterlace_mode": 0,
            "enabled": true,
            "flags": 0,
            "hotkeys": {
                "OBSBasic.SelectScene": [],
                "libobs.hide_scene_item.Video Capture Device (V4L2)": [],
                "libobs.show_scene_item.Video Capture Device (V4L2)": []
            },
            "id": "scene",
            "mixers": 0,
            "monitoring_type": 0,
            "muted": false,
            "name": "External Camera",
            "prev_ver": 436273154,
            "private_settings": {},
            "push-to-mute": false,
            "push-to-mute-delay": 0,
            "push-to-talk": false,
            "push-to-talk-delay": 0,
            "settings": {
                "custom_size": false,
                "id_counter": 1,
                "items": [
                    {
                        "align": 5,
                        "bounds": {
                            "x": 0.0,
                            "y": 0.0
                        },
                        "bounds_align": 0,
                        "bounds_type": 0,
                        "crop_bottom": 0,
                        "crop_left": 0,
                        "crop_right": 0,
                        "crop_top": 0,
                        "group_item_backup": false,
                        "id": 1,
                        "locked": false,
                        "name": "Video Capture Device (V4L2)",
                        "pos": {
                            "x": 0.0,
                            "y": 0.0
                        },
                        "private_settings": {},
                        "rot": 0.0,
                        "scale": {
                            "x": 1.0,
                            "y": 1.0
                        },
                        "scale_filter": "disable",
                        "visible": true
                    }
                ]
            },
            "sync": 0,
            "versioned_id": "scene",
            "volume": 1.0
        },
        {
            "balance": 0.5,
            "deinterlace_field_order": 0,
            "deinterlace_mode": 0,
            "enabled": true,
            "flags": 0,
            "hotkeys": {},
            "id": "image_source",
            "mixers": 0,
            "monitoring_type": 0,
            "muted": false,
            "name": "Logo",
            "prev_ver": 436273154,
            "private_settings": {},
            "push-to-mute": false,
            "push-to-mute-delay": 0,
            "push-to-talk": false,
            "push-to-talk-delay": 0,
            "settings": {
                "file": "/home/nharrington/projects/OBS_Cordince/imagery/Cordince_Logo.png"
            },
            "sync": 0,
            "versioned_id": "image_source",
            "volume": 1.0
        },
        {
            "balance": 0.5,
            "deinterlace_field_order": 0,
            "deinterlace_mode": 0,
            "enabled": true,
            "filters": [
                {
                    "balance": 0.5,
                    "deinterlace_field_order": 0,
                    "deinterlace_mode": 0,
                    "enabled": true,
                    "flags": 0,
                    "hotkeys": {},
                    "id": "color_filter",
                    "mixers": 0,
                    "monitoring_type": 0,
                    "muted": false,
                    "name": "Color Correction",
                    "prev_ver": 436273154,
                    "private_settings": {},
                    "push-to-mute": false,
                    "push-to-mute-delay": 0,
                    "push-to-talk": false,
                    "push-to-talk-delay": 0,
                    "settings": {
                        "brightness": -0.20000000000000001,
                        "saturation": -0.54000000000000004
                    },
                    "sync": 0,
                    "versioned_id": "color_filter",
                    "volume": 1.0
                },
                {
                    "balance": 0.5,
                    "deinterlace_field_order": 0,
                    "deinterlace_mode": 0,
                    "enabled": true,
                    "flags": 0,
                    "hotkeys": {},
                    "id": "streamfx-filter-blur",
                    "mixers": 0,
                    "monitoring_type": 0,
                    "muted": false,
                    "name": "Blur",
                    "prev_ver": 436273154,
                    "private_settings": {},
                    "push-to-mute": false,
                    "push-to-mute-delay": 0,
                    "push-to-talk": false,
                    "push-to-talk-delay": 0,
                    "settings": {
                        "Commit": "c6fb402d",
                        "Filter.Blur.Mask": true,
                        "Filter.Blur.Mask.Region.Bottom": 69.390000000000001,
                        "Filter.Blur.Mask.Region.Feather": 12.779999999999999,
                        "Filter.Blur.Mask.Region.Top": 0,
                        "Filter.Blur.Size": 17,
                        "Version": 38654836736
                    },
                    "sync": 0,
                    "versioned_id": "streamfx-filter-blur",
                    "volume": 1.0
                }
            ],
            "flags": 0,
            "hotkeys": {
                "MediaSource.Pause": [],
                "MediaSource.Play": [],
                "MediaSource.Restart": [],
                "MediaSource.Stop": [],
                "libobs.mute": [],
                "libobs.push-to-mute": [],
                "libobs.push-to-talk": [],
                "libobs.unmute": []
            },
            "id": "ffmpeg_source",
            "mixers": 255,
            "monitoring_type": 0,
            "muted": false,
            "name": "Bokeh Desaturated Top Blur",
            "prev_ver": 436273154,
            "private_settings": {},
            "push-to-mute": false,
            "push-to-mute-delay": 0,
            "push-to-talk": false,
            "push-to-talk-delay": 0,
            "settings": {
                "hw_decode": true,
                "local_file": "/home/nharrington/projects/OBS_Cordince/videos/hd_bokeh_circles.mp4",
                "looping": true,
                "restart_on_activate": false
            },
            "sync": 0,
            "versioned_id": "ffmpeg_source",
            "volume": 1.0
        },
        {
            "balance": 0.5,
            "deinterlace_field_order": 0,
            "deinterlace_mode": 0,
            "enabled": true,
            "flags": 0,
            "hotkeys": {},
            "id": "text_ft2_source",
            "mixers": 0,
            "monitoring_type": 0,
            "muted": false,
            "name": "Cordince",
            "prev_ver": 436273154,
            "private_settings": {},
            "push-to-mute": false,
            "push-to-mute-delay": 0,
            "push-to-talk": false,
            "push-to-talk-delay": 0,
            "settings": {
                "drop_shadow": true,
                "font": {
                    "face": "Proxima Nova",
                    "flags": 1,
                    "size": 72,
                    "style": "Bold"
                },
                "outline": true,
                "text": "CORDINCE"
            },
            "sync": 0,
            "versioned_id": "text_ft2_source_v2",
            "volume": 1.0
        },
        {
            "balance": 0.5,
            "deinterlace_field_order": 0,
            "deinterlace_mode": 0,
            "enabled": true,
            "flags": 0,
            "hotkeys": {
                "OBSBasic.SelectScene": [],
                "libobs.hide_scene_item.Cordince Center TItle": [],
                "libobs.hide_scene_item.Left Fire Up": [],
                "libobs.show_scene_item.Cordince Center TItle": [],
                "libobs.show_scene_item.Left Fire Up": []
            },
            "id": "scene",
            "mixers": 0,
            "monitoring_type": 0,
            "muted": false,
            "name": "Lobby Fire",
            "prev_ver": 436273154,
            "private_settings": {},
            "push-to-mute": false,
            "push-to-mute-delay": 0,
            "push-to-talk": false,
            "push-to-talk-delay": 0,
            "settings": {
                "custom_size": false,
                "id_counter": 2,
                "items": [
                    {
                        "align": 5,
                        "bounds": {
                            "x": 1920.0,
                            "y": 1080.0
                        },
                        "bounds_align": 0,
                        "bounds_type": 2,
                        "crop_bottom": 0,
                        "crop_left": 0,
                        "crop_right": 0,
                        "crop_top": 0,
                        "group_item_backup": false,
                        "id": 2,
                        "locked": false,
                        "name": "Left Fire Up",
                        "pos": {
                            "x": 0.0,
                            "y": 0.0
                        },
                        "private_settings": {},
                        "rot": 0.0,
                        "scale": {
                            "x": 1.0,
                            "y": 1.0
                        },
                        "scale_filter": "disable",
                        "visible": true
                    },
                    {
                        "align": 5,
                        "bounds": {
                            "x": 0.0,
                            "y": 0.0
                        },
                        "bounds_align": 0,
                        "bounds_type": 0,
                        "crop_bottom": 0,
                        "crop_left": 0,
                        "crop_right": 0,
                        "crop_top": 0,
                        "group_item_backup": false,
                        "id": 1,
                        "locked": false,
                        "name": "Cordince Center TItle",
                        "pos": {
                            "x": 0.0,
                            "y": 0.0
                        },
                        "private_settings": {},
                        "rot": 0.0,
                        "scale": {
                            "x": 1.0,
                            "y": 1.0
                        },
                        "scale_filter": "disable",
                        "visible": true
                    }
                ]
            },
            "sync": 0,
            "versioned_id": "scene",
            "volume": 1.0
        },
        {
            "balance": 0.5,
            "deinterlace_field_order": 0,
            "deinterlace_mode": 0,
            "enabled": true,
            "flags": 0,
            "hotkeys": {
                "OBSBasic.SelectScene": [],
                "libobs.hide_scene_item.Cordince": [],
                "libobs.hide_scene_item.Joining shortly": [],
                "libobs.hide_scene_item.Logo": [],
                "libobs.show_scene_item.Cordince": [],
                "libobs.show_scene_item.Joining shortly": [],
                "libobs.show_scene_item.Logo": []
            },
            "id": "scene",
            "mixers": 0,
            "monitoring_type": 0,
            "muted": false,
            "name": "Cordince Center TItle",
            "prev_ver": 436273154,
            "private_settings": {},
            "push-to-mute": false,
            "push-to-mute-delay": 0,
            "push-to-talk": false,
            "push-to-talk-delay": 0,
            "settings": {
                "custom_size": false,
                "id_counter": 5,
                "items": [
                    {
                        "align": 5,
                        "bounds": {
                            "x": 0.0,
                            "y": 0.0
                        },
                        "bounds_align": 0,
                        "bounds_type": 0,
                        "crop_bottom": 0,
                        "crop_left": 0,
                        "crop_right": 0,
                        "crop_top": 0,
                        "group_item_backup": false,
                        "id": 3,
                        "locked": true,
                        "name": "Joining shortly",
                        "pos": {
                            "x": 819.5,
                            "y": 287.0
                        },
                        "private_settings": {},
                        "rot": 0.0,
                        "scale": {
                            "x": 1.0,
                            "y": 1.0
                        },
                        "scale_filter": "disable",
                        "visible": true
                    },
                    {
                        "align": 5,
                        "bounds": {
                            "x": 0.0,
                            "y": 0.0
                        },
                        "bounds_align": 0,
                        "bounds_type": 0,
                        "crop_bottom": 0,
                        "crop_left": 0,
                        "crop_right": 0,
                        "crop_top": 0,
                        "group_item_backup": false,
                        "id": 4,
                        "locked": true,
                        "name": "Logo",
                        "pos": {
                            "x": 683.0,
                            "y": 141.0
                        },
                        "private_settings": {},
                        "rot": 0.0,
                        "scale": {
                            "x": 0.11999999731779099,
                            "y": 0.11999999731779099
                        },
                        "scale_filter": "disable",
                        "visible": true
                    },
                    {
                        "align": 5,
                        "bounds": {
                            "x": 0.0,
                            "y": 0.0
                        },
                        "bounds_align": 0,
                        "bounds_type": 0,
                        "crop_bottom": 0,
                        "crop_left": 0,
                        "crop_right": 0,
                        "crop_top": 0,
                        "group_item_backup": false,
                        "id": 5,
                        "locked": true,
                        "name": "Cordince",
                        "pos": {
                            "x": 812.0,
                            "y": 160.0
                        },
                        "private_settings": {},
                        "rot": 0.0,
                        "scale": {
                            "x": 1.0,
                            "y": 1.0
                        },
                        "scale_filter": "disable",
                        "visible": true
                    }
                ]
            },
            "sync": 0,
            "versioned_id": "scene",
            "volume": 1.0
        },
        {
            "balance": 0.5,
            "deinterlace_field_order": 0,
            "deinterlace_mode": 0,
            "enabled": true,
            "filters": [
                {
                    "balance": 0.5,
                    "deinterlace_field_order": 0,
                    "deinterlace_mode": 0,
                    "enabled": true,
                    "flags": 0,
                    "hotkeys": {},
                    "id": "color_filter",
                    "mixers": 0,
                    "monitoring_type": 0,
                    "muted": false,
                    "name": "Color Correction",
                    "prev_ver": 436273154,
                    "private_settings": {},
                    "push-to-mute": false,
                    "push-to-mute-delay": 0,
                    "push-to-talk": false,
                    "push-to-talk-delay": 0,
                    "settings": {
                        "gamma": -0.81999999999999995
                    },
                    "sync": 0,
                    "versioned_id": "color_filter",
                    "volume": 1.0
                }
            ],
            "flags": 0,
            "hotkeys": {
                "MediaSource.Pause": [],
                "MediaSource.Play": [],
                "MediaSource.Restart": [],
                "MediaSource.Stop": [],
                "libobs.mute": [],
                "libobs.push-to-mute": [],
                "libobs.push-to-talk": [],
                "libobs.unmute": []
            },
            "id": "ffmpeg_source",
            "mixers": 255,
            "monitoring_type": 0,
            "muted": false,
            "name": "Left Fire Up",
            "prev_ver": 436273154,
            "private_settings": {},
            "push-to-mute": false,
            "push-to-mute-delay": 0,
            "push-to-talk": false,
            "push-to-talk-delay": 0,
            "settings": {
                "hw_decode": true,
                "local_file": "/home/nharrington/projects/OBS_Cordince/videos/hd_vertical_glow.mp4",
                "looping": true,
                "restart_on_activate": false
            },
            "sync": 0,
            "versioned_id": "ffmpeg_source",
            "volume": 1.0
        }
    ],
    "transition_duration": 300,
    "transitions": []
}